Workbook

Sheet Instrucciones
B2: • Esta plantilla sirve para: (1) ver la distribución actual de tu portafolio, (2) seguir la evolución del patrimonio total y del dinero en billetera virtual, y (3) obtener alertas y análisis descriptivos (no asesoría financiera). | D2: IMPORTANTE! Para calcular la ganancia periódica en billeteras virtuales que generan rendimiento
B3: • Hoja "Activos": pega o carga tus posiciones actuales. Puedes reemplazar los datos de ejemplo por exportaciones de tu broker o exchange. | D3: es necesario restar gastos y sumar ingresos del saldo inicial en donde figura la cantidad de pesos
B4: • Hoja "Evolución": registra por fecha el valor total del portafolio y el saldo de la billetera virtual. Si pegas un historial periódico, el dashboard se actualiza solo. | D4: e ingresar el saldo actual donde figura el valor actual
B5: • Hoja "Dashboard": muestra indicadores y gráficos en automático. Las métricas se recalculan cuando cambias los datos de las hojas anteriores.
B6: • Automatización recomendada #1 (sin programar): exporta CSV/XLSX desde tu broker y billetera, y usa Power Query en Excel para importarlos y actualizar con un clic. | D6: IMPORTANTE! CARGAR PRECIO DEL DÓLAR SEMANALMENTE Y ANOTAR LA TASA DE INFLACIÓN
B7: • Automatización recomendada #2 (con API): si tu broker/exchange/billetera ofrece API, puedes conectarla con Power Query, Office Scripts o Python para refrescar precios, movimientos y saldos. | D7: MENSUALMENTE A PARTIR DEL PRIMER MES TRANSCURRRIDO TENIENDO EN CUENTA LA ULTIMA
B8: • Automatización recomendada #3 (Google Sheets/Excel Online): puedes centralizar datos en una tabla maestra y conectar Excel a esa fuente. | D8: TASA DE INFLACIÓN DISPONIBLE
B10: TUTORIAL RECOMENDADO: Desde tu broker o página que utilizás para invertir, exporta los datos a un | D10: Chequeá la inlflación en el link
B11: chat específico con la IA que utilizes habitualmente y pídele que te separe los datos para pegar en una | D11: https://www.indec.gob.ar/
B12: planilla de excel.
D13: Pasos recomendados
B14: IMPORTANTE! Cada carga nueva deberás anotar el nuevo precio de cada activo y se recomienda anotar el resultado de un activo si este se va a vender/gastar/etc. Asi cuando se borra la fila no se pierden los resultados para ese activo. (Se debe borrar los datos de los activos que ya no posee para no afectar los porcentajes) | D14: 1. Exportar estado de cuenta del broker.
D15: 2. Actualizar precios actuales.
D16: 3. Actualizar saldo de billetera.
D17: 4. Agregar una fila en Evolución.
D18: 5. Revisar Dashboard.

Sheet Activos
A1: Ticker | B1: Nombre | C1: Clase de activo | D1: Moneda | E1: Cantidad | F1: Precio promedio compra | G1: Precio actual | H1: Valor actual | I1: Resultado | J1: % del portafolio
H2: =E2*G2 -> 0 | I2: =E2*(G2-F2) -> 0 | J2: =IFERROR(H2/SUM($H$2:$H$1000),"") | L2: Resumen
H3: =E3*G3 -> 0 | I3: =E3*(G3-F3) -> 0 | J3: =IFERROR(H3/SUM($H$2:$H$1000),"") | L3: Valor portafolio | M3: =M9+M10 -> 0
H4: =E4*G4 -> 0 | I4: =E4*(G4-F4) -> 0 | J4: =IFERROR(H4/SUM($H$2:$H$1000),"") | L4: Resultado | M4: =SUM(I2:I21) -> 0
H5: =E5*G5 -> 0 | I5: =E5*(G5-F5) -> 0 | J5: =IFERROR(H5/SUM($H$2:$H$1000),"") | L5: Activo más concentrado | M5: =MAX(J2:J21) -> 0
H6: =E6*G6 -> 0 | I6: =E6*(G6-F6) -> 0 | J6: =IFERROR(H6/SUM($H$2:$H$1000),"") | L6: Moneda | M6: =M11+M12+M13 -> 0
H7: =E7*G7 -> 0 | I7: =E7*(G7-F7) -> 0 | J7: =IFERROR(H7/SUM($H$2:$H$1000),"")
H8: =E8*G8 -> 0 | I8: =E8*(G8-F8) -> 0 | J8: =IFERROR(H8/SUM($H$2:$H$1000),"") | L8: Clase | M8: Valor
H9: =E9*G9 -> 0 | I9: =E9*(G9-F9) -> 0 | J9: =IFERROR(H9/SUM($H$2:$H$1000),"") | L9: Acciones | M9: =SUMIF($C$2:$C$21,L9,$H$2:$H$21) -> 0
H10: =E10*G10 -> 0 | I10: =H10-E10 -> 0 | J10: =IFERROR(H10/SUM($H$2:$H$1000),"") | L10: CEDEARS | M10: =SUMIF($C$2:$C$21,L10,$H$2:$H$21) -> 0
H11: =E11*G11 -> 0 | I11: =E11*(G11-F11) -> 0 | J11: =IFERROR(H11/SUM($H$2:$H$1000),"") | L11: Billetera Virtual | M11: =SUMIF($C$2:$C$21,L11,$H$2:$H$21) -> 0
H12: =E12*G12 -> 0 | I12: =E12*(G12-F12) -> 0 | L12: Efectivo(USD) | M12: =SUMIF($C$2:$C$21,L12,$H$2:$H$21) -> 0
H13: =E13*G13 -> 0 | I13: =E13*(G13-F13) -> 0 | L13: Efectivo(ARS) | M13: =SUMIF($C$2:$C$21,L13,$H$2:$H$21) -> 0
L14: Otros | M14: =SUMIF($C$2:$C$21,L14,$H$2:$H$21) -> 0

Sheet Evolución
A1: Fecha | B1: Valor portafolio | C1: Saldo billetera virtual | D1: Dolares | E1: Pesos | F1: Tasa inflación mensual (mes anterior) | G1: Patrimonio total | H1: Evolución periódica
E2: 0 | F2: 0 | G2: =B2+C2+D2+E2 -> 0 | I2: Indicadores
H3: =IFERROR((G3/G2)-1,"") | I3: Patrimonio inicial | J3: {=INDEX(G2:G200,MATCH(TRUE,G2:G200<>"",0))} -> 0
H4: =IFERROR((G4/G3)-1,"") | I4: Patrimonio actual | J4: {=LOOKUP(2,1/(G2:G9<>""),G2:G9)} -> 0
I5: Variación acumulada | J5: =IFERROR((J4/J3)-1,0) -> 0
I6: Billetera inicial | J6: =C2 -> 0
I7: Billetera actual | J7: {=LOOKUP(2,1/(C2:C200<>""),C2:C200)} -> #N/A
I8: Variación billetera | J8: =IFERROR((J7/J6)-1,0) -> 0
I9: Inflación | J9: {=PRODUCT(1+F2:F100)-1} -> 0
I10: Poder Adquisitivo | J10: =J5-J9 -> 0 | K10: =IF(J10>0,"","Perdés contra inflación") -> Perdés contra inflación
K11: =IF(J10>0,"Le ganás a inflación","")

Sheet Dashboard
B2: Dashboard
B4: Valor portafolio actual | D4: Resultado no realizado | F4: Activo más concentrado
B5: =Activos!M3 -> 0 | D5: =Activos!M4 -> 0 | F5: =Activos!M5 -> 0
B7: Saldo billetera actual | D7: Patrimonio total actual | F7: Variación patrimonio | H7: Liquidez
B8: =Evolución!J7 -> #N/A | D8: =Evolución!J4 -> 0 | F8: =Evolución!J5 -> 0 | I8: =(Activos!M13+Activos!M12+Activos!M11)/Evolución!G2 -> #DIV/0!
B11: Lectura rápida (descriptiva, no recomendación financiera)
B12: • Si el activo más concentrado supera tu límite objetivo (por ejemplo 20%-30%), tienes riesgo de concentración.
B13: • Si la billetera virtual sube demasiado versus el patrimonio total, quizá estás acumulando liquidez sin asignarla a tu estrategia.
B14: • Compara la variación de patrimonio con tu benchmark para revisar si el portafolio acompaña tu objetivo.
B15: • Observa la mezcla por clase de activo para ver si la exposición a ARS/USD o a activos volátiles coincide con tu tolerancia al riesgo.
B18: Tip: si conviertes tus exportaciones a tablas con el mismo esquema, solo pega filas nuevas y todo el dashboard se actualiza.
